example.ini
gmcapsule/__init__.py
gmcapsule/gemini.py
gmcapsule/markdown.py
gmcapsule/modules/10_rewrite.py
gmcapsule/modules/80_gitview.py
gmcapsule/modules/80_misfin.py
gmcapsule/modules/90_cgi.py
gmcapsule/modules/99_static.py
gmcapsule-0.9.8.dist-info/METADATA
gmcapsule-0.9.8.dist-info/WHEEL
gmcapsule-0.9.8.dist-info/entry_points.txt
gmcapsule-0.9.8.dist-info/RECORD
