Metadata-Version: 2.1
Name: gmcapsule
Version: 0.9.8
Summary: Extensible Gemini/Titan server
Project-URL: Home-page, https://geminispace.org/gmcapsule/
Project-URL: Documentation, https://geminispace.org/gmcapsule/gmcapsule.html
Project-URL: Source, https://codeberg.org/skyjake/gmcapsule
Project-URL: Issues, https://codeberg.org/skyjake/gmcapsule/issues
Author-email: Jaakko Keränen <jaakko.keranen@iki.fi>
Keywords: gemini,internet,server,titan
Classifier: Development Status :: 4 - Beta
Classifier: Intended Audience :: Information Technology
Classifier: Intended Audience :: System Administrators
Classifier: License :: OSI Approved :: BSD License
Classifier: Programming Language :: Python
Classifier: Programming Language :: Python :: 3.6
Classifier: Topic :: Internet
Classifier: Topic :: System :: Networking
Requires-Python: >=3.6
Requires-Dist: pyopenssl>=21
